intake/__init__.py
intake/_version.py
intake/config.py
intake/conftest.py
intake/util_tests.py
intake/utils.py
intake/catalog/__init__.py
intake/catalog/base.py
intake/catalog/default.py
intake/catalog/entry.py
intake/catalog/exceptions.py
intake/catalog/gui.py
intake/catalog/local.py
intake/catalog/utils.py
intake/catalog/zarr.py
intake/container/__init__.py
intake/container/base.py
intake/interface/__init__.py
intake/interface/base.py
intake/interface/gui.py
intake/interface/catalog/__init__.py
intake/interface/catalog/add.py
intake/interface/catalog/search.py
intake/interface/source/__init__.py
intake/interface/source/defined_plots.py
intake/readers/__init__.py
intake/readers/catalogs.py
intake/readers/convert.py
intake/readers/datatypes.py
intake/readers/entry.py
intake/readers/examples.py
intake/readers/importlist.py
intake/readers/metadata.py
intake/readers/mixins.py
intake/readers/namespaces.py
intake/readers/output.py
intake/readers/readers.py
intake/readers/search.py
intake/readers/transform.py
intake/readers/user_parameters.py
intake/readers/utils.py
intake/source/__init__.py
intake/source/base.py
intake/source/csv.py
intake/source/derived.py
intake/source/discovery.py
intake/source/jsonfiles.py
intake/source/npy.py
intake/source/textfiles.py
intake/source/tiled.py
intake/source/utils.py
intake/source/zarr.py
intake-2.0.8.dist-info/LICENSE
intake-2.0.8.dist-info/METADATA
intake-2.0.8.dist-info/WHEEL
intake-2.0.8.dist-info/entry_points.txt
intake-2.0.8.dist-info/top_level.txt
intake-2.0.8.dist-info/RECORD
