Metadata-Version: 2.2
Name: intake
Version: 2.0.8
Summary: Data catalog, search and load
Author-email: Martin Durant <martin.durant@alumni.utoronto.ca>
License: MIT
Classifier: License :: OSI Approved :: MIT License
Classifier: Operating System :: OS Independent
Classifier: Programming Language :: Python
Classifier: Development Status :: 4 - Beta
Requires-Python: >=3.8
License-File: LICENSE
Requires-Dist: fsspec>=2023.0.0
Requires-Dist: pyyaml
Requires-Dist: platformdirs
Requires-Dist: networkx
